gawp/__init__.py
gawp/gawp.py
gawp/html.py
gawp/html_template.py
gawp/request_handler.py
gawp/server.py
gawp/template.html
gawp/types_and_default_values.py
gawp-2025.2.4.dist-info/METADATA
gawp-2025.2.4.dist-info/WHEEL
gawp-2025.2.4.dist-info/licenses/LICENSE
gawp-2025.2.4.dist-info/RECORD
