Metadata-Version: 2.4
Name: gawp
Version: 2025.2.4
Summary: A package for displaying images in a web browser
Project-URL: Homepage, https://https://github.com/tenghamn/gawp
Project-URL: Bug Tracker, https://https://github.com/tenghamn/gawp/issues
Author-email: Johan Tenghamn <johan.tenghamn@gmail.com>
License-Expression: MIT
License-File: LICENSE
Classifier: License :: OSI Approved :: MIT License
Classifier: Operating System :: OS Independent
Classifier: Programming Language :: Python :: 3
Classifier: Topic :: Multimedia :: Graphics :: Viewers
Classifier: Topic :: Scientific/Engineering
Classifier: Topic :: Software Development
Classifier: Typing :: Typed
Requires-Python: >=3.8
Requires-Dist: ipython
Requires-Dist: matplotlib
Requires-Dist: numpy
Requires-Dist: pillow
Requires-Dist: scikit-image
